pipegraph/__init__.py
pipegraph/adapters.py
pipegraph/base.py
pipegraph/demo_blocks.py
pipeGraph-0.3.3.dist-info/LICENSE.txt
pipeGraph-0.3.3.dist-info/METADATA
pipeGraph-0.3.3.dist-info/WHEEL
pipeGraph-0.3.3.dist-info/top_level.txt
pipeGraph-0.3.3.dist-info/RECORD
