Metadata-Version: 2.1
Name: pipeGraph
Version: 0.3.3
Summary: PipeGraph extends the concept of Scikit-Learn's Pipeline tool
Home-page: https://mcasl.github.io/PipeGraph/
Author: See License.txt file in source package
Author-email: manuel.castejon@unileon.es
License: MIT
Keywords: scikit-learn pipeline development
Platform: UNKNOWN
Classifier: Intended Audience :: Science/Research
Classifier: Intended Audience :: Developers
Classifier: License :: OSI Approved :: MIT License
Classifier: Topic :: Software Development
Classifier: Topic :: Scientific/Engineering
Classifier: Operating System :: Microsoft :: Windows
Classifier: Operating System :: POSIX
Classifier: Operating System :: Unix
Classifier: Operating System :: MacOS
Classifier: Programming Language :: Python :: 3.6
Requires-Python: >=3
Requires-Dist: pytest
Requires-Dist: scikit-learn (>=0.17)
Requires-Dist: networkx
Requires-Dist: pandas
Provides-Extra: dev
Requires-Dist: check-manifest ; extra == 'dev'
Provides-Extra: test
Requires-Dist: coverage ; extra == 'test'
